spider_download/__init__.py
spider_download/decorators.py
spider_download/spider.py
spider_download-1.0.12.dist-info/METADATA
spider_download-1.0.12.dist-info/WHEEL
spider_download-1.0.12.dist-info/top_level.txt
spider_download-1.0.12.dist-info/RECORD
