Metadata-Version: 2.4
Name: spider-download
Version: 1.0.12
Summary: 多线程下载
Author-email: funcdefmain <741132517@qq.com>
License: MIT
Requires-Python: >=3.8
Requires-Dist: requests
Requires-Dist: tqdm
Requires-Dist: loguru
